astroconst/__init__.py
astroconst/aa.py
astroconst-0.0.14.dist-info/licenses/LICENCE
astroconst-0.0.14.dist-info/METADATA
astroconst-0.0.14.dist-info/WHEEL
astroconst-0.0.14.dist-info/top_level.txt
astroconst-0.0.14.dist-info/RECORD
