Metadata-Version: 2.4
Name: astroconst
Version: 0.0.14
Summary: A Python package that provides astronomical constants.
Author-email: Marc van der Sluys <git@vandersluys.nl>
License-Expression: EUPL-1.2
Project-URL: GitHub, https://github.com/MarcvdSluys/AstroConst
Project-URL: ReadTheDocs, https://astroconst.readthedocs.io
Keywords: constants,astronomy,physics,mathematics
Classifier: Development Status :: 3 - Alpha
Classifier: Intended Audience :: Developers
Classifier: Intended Audience :: Education
Classifier: Intended Audience :: Science/Research
Classifier: Natural Language :: English
Classifier: Operating System :: OS Independent
Classifier: Programming Language :: Python :: 3
Classifier: Topic :: Scientific/Engineering
Classifier: Topic :: Scientific/Engineering :: Astronomy
Classifier: Topic :: Scientific/Engineering :: Physics
License-File: LICENCE
Requires-Dist: numpy
Dynamic: license-file
